setup.py
TweetFS.egg-info/PKG-INFO
TweetFS.egg-info/SOURCES.txt
TweetFS.egg-info/dependency_links.txt
TweetFS.egg-info/top_level.txt
bin/tweetfs
tweetfs/__init__.py
tweetfs/comm.py
tweetfs/hide.py
tweetfs/pack.py
tweetfs/payload.py
tweetfs/test.py
tweetfs/tweetfs.py
tweetfs/twitter.py
tweetfs/unpack.py
tweetfs/util.py
tweetfs/x.py