Metadata-Version: 1.1
Name: TweetFS
Version: 0.1
Summary: Clandestinely store small files and directories on Twitter.
Home-page: http://github.com/rw/tweetfs
Author: Robert Winslow
Author-email: robert.winslow@gmail.com
License: UNKNOWN
Platform: UNKNOWN
Classifier: Development Status :: 3 - Alpha
Classifier: Intended Audience :: Developers
Classifier: Intended Audience :: End Users/Desktop
Classifier: Natural Language :: English
Classifier: Programming Language :: Python
Classifier: Topic :: Text Processing :: Filters
Classifier: Topic :: Text Processing :: Linguistic
Requires: bitstring
Requires: Plainsight (==1.1.2)
Requires: SeqTweet (==0.1)
